codeaskcli/__init__.py
codeaskcli/analyzer.py
codeaskcli/api.py
codeaskcli/cli.py
codeaskcli/config.py
codeaskcli/file_utils.py
codeaskcli/main.py
codeaskcli/templates.py
codeaskcli/tui.py
codeaskcli-0.1.2.dist-info/METADATA
codeaskcli-0.1.2.dist-info/WHEEL
codeaskcli-0.1.2.dist-info/entry_points.txt
codeaskcli-0.1.2.dist-info/top_level.txt
codeaskcli-0.1.2.dist-info/RECORD
