Metadata-Version: 2.4
Name: codeaskcli
Version: 0.1.2
Summary: 根据代码调用llm自动生成解析文档
Author-email: shadow3 <shadow3aaaa@gmail.com>
Requires-Python: >=3.12
Requires-Dist: requests>=2.32.3
Requires-Dist: simplejson>=3.20.1
Requires-Dist: zstandard>=0.23.0
Requires-Dist: tomli>=2.0.1
Requires-Dist: pyyaml>=6.0.1
Requires-Dist: rich>=13.7.0
